Workbook

Sheet Produtos Bazar
A1: CONTROLE DO BAZAR — PURE PERFUMARIA
A2: Cadastre cada item promocional. As colunas de vendas, estoque, desconto e status são automáticas.
A3: Última atualização: | B3: 46288
A5: Produtos cadastrados | B5: =COUNTIF(A8:A107,"<>") -> 0 | D5: Unidades disponíveis | E5: =SUM(I8:I107) -> 52 | G5: Valor potencial de venda | H5: =SUMPRODUCT(I8:I107,K8:K107) -> 8389.796 | J5: Itens esgotados | K5: =COUNTIF(M8:M107,"ESGOTADO") -> 0
A7: Código | B7: Produto | C7: Marca | D7: Categoria | E7: Volume / Tamanho | F7: Condição / Avaria da Caixa | G7: Qtd. Inicial | H7: Qtd. Vendida | I7: Estoque Atual | J7: Preço Original | K7: Preço Promo | L7: Desconto % | M7: Status | N7: Localização | O7: Observações | P7: Data Cadastro
B8: CLUB DE NUIT INTENSE MEN | C8: ARMAF | D8: PERFUME | F8: CAIXA COM PEQUENAS AVARIAS | G8: 15 | H8: 0 | I8: 15 | J8: 275.99 | K8: =IF(OR(J8="",L8=""),"",J8*(1-L8)) -> 165.594 | L8: 0.4 | M8: =IF(INDEX(A:A,ROW())="","",IF(INDEX(I:I,ROW())<=0,"ESGOTADO",IF(INDEX(I:I,ROW())<=2,"ÚLTIMAS UNIDADES","DISPONÍVEL"))) | P8: 46288
B9: SABAH AL WARD | C9: AL WATANIAH | D9: PERFUME | F9: CAIXA COM PEQUENAS AVARIAS | G9: 3 | H9: {=IF(INDEX(A:A,ROW())="","",SUMIF(Vendas!$B$5:$B$504,INDEX(A:A,ROW()),Vendas!$D$5:$D$504))} | I9: 3 | J9: 229 | K9: =IF(OR(J9="",L9=""),"",J9*(1-L9)) -> 160.3 | L9: 0.3 | M9: =IF(INDEX(A:A,ROW())="","",IF(INDEX(I:I,ROW())<=0,"ESGOTADO",IF(INDEX(I:I,ROW())<=2,"ÚLTIMAS UNIDADES","DISPONÍVEL")))
B10: CLUB DE NUIT ICONIC | C10: ARMAF | D10: PERFUME | F10: AVARIA NA CAIXA E PRODUTO ABERTO | G10: 6 | H10: {=IF(INDEX(A:A,ROW())="","",SUMIF(Vendas!$B$5:$B$504,INDEX(A:A,ROW()),Vendas!$D$5:$D$504))} | I10: 6 | J10: 399.9 | K10: =IF(OR(J10="",L10=""),"",J10*(1-L10)) -> 239.94 | L10: 0.4 | M10: =IF(INDEX(A:A,ROW())="","",IF(INDEX(I:I,ROW())<=0,"ESGOTADO",IF(INDEX(I:I,ROW())<=2,"ÚLTIMAS UNIDADES","DISPONÍVEL")))
B11: CLUB DE NUIT URBAN MAN | C11: ARMAF | D11: PERFUME | F11: SEM CAIXA | G11: 1 | H11: {=IF(INDEX(A:A,ROW())="","",SUMIF(Vendas!$B$5:$B$504,INDEX(A:A,ROW()),Vendas!$D$5:$D$504))} | I11: 1 | J11: 349 | K11: =IF(OR(J11="",L11=""),"",J11*(1-L11)) -> 209.4 | L11: 0.4 | M11: =IF(INDEX(A:A,ROW())="","",IF(INDEX(I:I,ROW())<=0,"ESGOTADO",IF(INDEX(I:I,ROW())<=2,"ÚLTIMAS UNIDADES","DISPONÍVEL")))
B12: CHANTS TANDERINA | D12: PERFUME | F12: CAIXA COM AVARIA E ABERTOS | G12: 2 | H12: {=IF(INDEX(A:A,ROW())="","",SUMIF(Vendas!$B$5:$B$504,INDEX(A:A,ROW()),Vendas!$D$5:$D$504))} | I12: 2 | J12: 199 | K12: =IF(OR(J12="",L12=""),"",J12*(1-L12)) -> 119.4 | L12: 0.4 | M12: =IF(INDEX(A:A,ROW())="","",IF(INDEX(I:I,ROW())<=0,"ESGOTADO",IF(INDEX(I:I,ROW())<=2,"ÚLTIMAS UNIDADES","DISPONÍVEL")))
B13: FERRARI BLACK | C13: FERRARI | D13: PERFUME | F13: CAIXA COM AVARIAS | G13: 1 | H13: {=IF(INDEX(A:A,ROW())="","",SUMIF(Vendas!$B$5:$B$504,INDEX(A:A,ROW()),Vendas!$D$5:$D$504))} | I13: 1 | J13: 219.89 | K13: =IF(OR(J13="",L13=""),"",J13*(1-L13)) -> 131.934 | L13: 0.4 | M13: =IF(INDEX(A:A,ROW())="","",IF(INDEX(I:I,ROW())<=0,"ESGOTADO",IF(INDEX(I:I,ROW())<=2,"ÚLTIMAS UNIDADES","DISPONÍVEL")))
B14: FLORATA | C14: OBOTICARIO | D14: PERFUME | F14: SEM CAIXA | G14: 1 | H14: {=IF(INDEX(A:A,ROW())="","",SUMIF(Vendas!$B$5:$B$504,INDEX(A:A,ROW()),Vendas!$D$5:$D$504))} | I14: 1 | J14: 115.8 | K14: =IF(OR(J14="",L14=""),"",J14*(1-L14)) -> 57.9 | L14: 0.5 | M14: =IF(INDEX(A:A,ROW())="","",IF(INDEX(I:I,ROW())<=0,"ESGOTADO",IF(INDEX(I:I,ROW())<=2,"ÚLTIMAS UNIDADES","DISPONÍVEL")))
B15: BARBOURS'S MY SWEET DELIGHT | C15: BARBOUR'S | D15: BODY SPLASH | F15: PRODUTO ÚTILIZADO' ABERTO | G15: 1 | H15: {=IF(INDEX(A:A,ROW())="","",SUMIF(Vendas!$B$5:$B$504,INDEX(A:A,ROW()),Vendas!$D$5:$D$504))} | I15: 1 | J15: 38.99 | K15: =IF(OR(J15="",L15=""),"",J15*(1-L15)) -> 38.99 | L15: 0 | M15: =IF(INDEX(A:A,ROW())="","",IF(INDEX(I:I,ROW())<=0,"ESGOTADO",IF(INDEX(I:I,ROW())<=2,"ÚLTIMAS UNIDADES","DISPONÍVEL")))
B16: LATAFFA EMMER | C16: LATAFFA | D16: PERFUME | F16: LUZ DE LED DA CAIXA NÃO ACENDE | G16: 1 | H16: {=IF(INDEX(A:A,ROW())="","",SUMIF(Vendas!$B$5:$B$504,INDEX(A:A,ROW()),Vendas!$D$5:$D$504))} | I16: 1 | J16: 329.9 | K16: =IF(OR(J16="",L16=""),"",J16*(1-L16)) -> 197.94 | L16: 0.4 | M16: =IF(INDEX(A:A,ROW())="","",IF(INDEX(I:I,ROW())<=0,"ESGOTADO",IF(INDEX(I:I,ROW())<=2,"ÚLTIMAS UNIDADES","DISPONÍVEL")))
B17: LATAFFA ASAD ELIXIR | C17: LATAFFA | D17: PERFUME | F17: PRODUTO ABERTO E CAIXA COM AVARIAS | G17: 1 | H17: {=IF(INDEX(A:A,ROW())="","",SUMIF(Vendas!$B$5:$B$504,INDEX(A:A,ROW()),Vendas!$D$5:$D$504))} | I17: 1 | J17: 239.9 | K17: =IF(OR(J17="",L17=""),"",J17*(1-L17)) -> 143.94 | L17: 0.4 | M17: =IF(INDEX(A:A,ROW())="","",IF(INDEX(I:I,ROW())<=0,"ESGOTADO",IF(INDEX(I:I,ROW())<=2,"ÚLTIMAS UNIDADES","DISPONÍVEL")))
B18: SIGNATURE | C18: MONTBLANC | D18: PERFUME | F18: PRODUTO COM AVARIA NA CAIXA | G18: 1 | H18: {=IF(INDEX(A:A,ROW())="","",SUMIF(Vendas!$B$5:$B$504,INDEX(A:A,ROW()),Vendas!$D$5:$D$504))} | I18: 1 | J18: 799 | K18: =IF(OR(J18="",L18=""),"",J18*(1-L18)) -> 479.4 | L18: 0.4 | M18: =IF(INDEX(A:A,ROW())="","",IF(INDEX(I:I,ROW())<=0,"ESGOTADO",IF(INDEX(I:I,ROW())<=2,"ÚLTIMAS UNIDADES","DISPONÍVEL")))
B19: CK ONE | C19: CALVIN KLEIN | D19: PERFUME | F19: PRODUTO SEM CAIXA E SPRAY | G19: 1 | H19: {=IF(INDEX(A:A,ROW())="","",SUMIF(Vendas!$B$5:$B$504,INDEX(A:A,ROW()),Vendas!$D$5:$D$504))} | I19: 1 | J19: 298.68 | K19: =IF(OR(J19="",L19=""),"",J19*(1-L19)) -> 179.208 | L19: 0.4 | M19: =IF(INDEX(A:A,ROW())="","",IF(INDEX(I:I,ROW())<=0,"ESGOTADO",IF(INDEX(I:I,ROW())<=2,"ÚLTIMAS UNIDADES","DISPONÍVEL")))
B20: CLUB DE NUIT WOMAN | C20: ARMAF | D20: PERFUME | F20: PRODUTO FOI ABERTO | G20: 1 | H20: {=IF(INDEX(A:A,ROW())="","",SUMIF(Vendas!$B$5:$B$504,INDEX(A:A,ROW()),Vendas!$D$5:$D$504))} | I20: 1 | J20: 279 | K20: =IF(OR(J20="",L20=""),"",J20*(1-L20)) -> 167.4 | L20: 0.4 | M20: =IF(INDEX(A:A,ROW())="","",IF(INDEX(I:I,ROW())<=0,"ESGOTADO",IF(INDEX(I:I,ROW())<=2,"ÚLTIMAS UNIDADES","DISPONÍVEL")))
B21: CLUB DE NUIT SILLAGE | C21: ARMAF | D21: PERFUME | F21: SEM CAIXA | G21: 1 | H21: {=IF(INDEX(A:A,ROW())="","",SUMIF(Vendas!$B$5:$B$504,INDEX(A:A,ROW()),Vendas!$D$5:$D$504))} | I21: 1 | J21: 328 | K21: =IF(OR(J21="",L21=""),"",J21*(1-L21)) -> 196.8 | L21: 0.4 | M21: =IF(INDEX(A:A,ROW())="","",IF(INDEX(I:I,ROW())<=0,"ESGOTADO",IF(INDEX(I:I,ROW())<=2,"ÚLTIMAS UNIDADES","DISPONÍVEL")))
B22: YARA TRADICIONAL | C22: LATAFFA | D22: PERFUME | F22: SEM CAIXA | G22: 2 | H22: {=IF(INDEX(A:A,ROW())="","",SUMIF(Vendas!$B$5:$B$504,INDEX(A:A,ROW()),Vendas!$D$5:$D$504))} | I22: 2 | J22: 249 | K22: =IF(OR(J22="",L22=""),"",J22*(1-L22)) -> 149.4 | L22: 0.4 | M22: =IF(INDEX(A:A,ROW())="","",IF(INDEX(I:I,ROW())<=0,"ESGOTADO",IF(INDEX(I:I,ROW())<=2,"ÚLTIMAS UNIDADES","DISPONÍVEL")))
B23: BAREEQ AL DHAHAB | C23: AL WATANIAH | D23: PERFUME | F23: CAIXA COM PEQUENAS AVARIAS | G23: 1 | H23: {=IF(INDEX(A:A,ROW())="","",SUMIF(Vendas!$B$5:$B$504,INDEX(A:A,ROW()),Vendas!$D$5:$D$504))} | I23: 1 | J23: 136.9 | K23: =IF(OR(J23="",L23=""),"",J23*(1-L23)) -> 82.14 | L23: 0.4 | M23: =IF(INDEX(A:A,ROW())="","",IF(INDEX(I:I,ROW())<=0,"ESGOTADO",IF(INDEX(I:I,ROW())<=2,"ÚLTIMAS UNIDADES","DISPONÍVEL")))
B24: AL NOBLE WAZEER | C24: LATAFFA | D24: PERFUME | F24: CAIXA COM AVARIAS | G24: 1 | H24: {=IF(INDEX(A:A,ROW())="","",SUMIF(Vendas!$B$5:$B$504,INDEX(A:A,ROW()),Vendas!$D$5:$D$504))} | I24: 1 | J24: 174.99 | K24: =IF(OR(J24="",L24=""),"",J24*(1-L24)) -> 104.994 | L24: 0.4 | M24: =IF(INDEX(A:A,ROW())="","",IF(INDEX(I:I,ROW())<=0,"ESGOTADO",IF(INDEX(I:I,ROW())<=2,"ÚLTIMAS UNIDADES","DISPONÍVEL")))
... B30: BODY SPLASH MARINA | C30: AVATIM | D30: SPLAY | F30: SEM CAIXA | G30: 4 | H30: {=IF(INDEX(A:A,ROW())="","",SUMIF(Vendas!$B$5:$B$504,INDEX(A:A,ROW()),Vendas!$D$5:$D$504))} | I30: 4 | J30: 106 | K30: =IF(OR(J30="",L30=""),"",J30*(1-L30)) -> 53 | L30: 0.5 | M30: =IF(INDEX(A:A,ROW())="","",IF(INDEX(I:I,ROW())<=0,"ESGOTADO",IF(INDEX(I:I,ROW())<=2,"ÚLTIMAS UNIDADES","DISPONÍVEL")))
H31: {=IF(INDEX(A:A,ROW())="","",SUMIF(Vendas!$B$5:$B$504,INDEX(A:A,ROW()),Vendas!$D$5:$D$504))} | I31: =IF(INDEX(A:A,ROW())="","",INDEX(G:G,ROW())-INDEX(H:H,ROW())) | K31: =IF(OR(J31="",L31=""),"",J31*(1-L31)) | M31: =IF(INDEX(A:A,ROW())="","",IF(INDEX(I:I,ROW())<=0,"ESGOTADO",IF(INDEX(I:I,ROW())<=2,"ÚLTIMAS UNIDADES","DISPONÍVEL")))
H32: {=IF(INDEX(A:A,ROW())="","",SUMIF(Vendas!$B$5:$B$504,INDEX(A:A,ROW()),Vendas!$D$5:$D$504))} | I32: =IF(INDEX(A:A,ROW())="","",INDEX(G:G,ROW())-INDEX(H:H,ROW())) | K32: =IF(OR(J32="",L32=""),"",J32*(1-L32)) | M32: =IF(INDEX(A:A,ROW())="","",IF(INDEX(I:I,ROW())<=0,"ESGOTADO",IF(INDEX(I:I,ROW())<=2,"ÚLTIMAS UNIDADES","DISPONÍVEL")))
H33: {=IF(INDEX(A:A,ROW())="","",SUMIF(Vendas!$B$5:$B$504,INDEX(A:A,ROW()),Vendas!$D$5:$D$504))} | I33: =IF(INDEX(A:A,ROW())="","",INDEX(G:G,ROW())-INDEX(H:H,ROW())) | K33: =IF(OR(J33="",L33=""),"",J33*(1-L33)) | M33: =IF(INDEX(A:A,ROW())="","",IF(INDEX(I:I,ROW())<=0,"ESGOTADO",IF(INDEX(I:I,ROW())<=2,"ÚLTIMAS UNIDADES","DISPONÍVEL")))
H34: {=IF(INDEX(A:A,ROW())="","",SUMIF(Vendas!$B$5:$B$504,INDEX(A:A,ROW()),Vendas!$D$5:$D$504))} | I34: =IF(INDEX(A:A,ROW())="","",INDEX(G:G,ROW())-INDEX(H:H,ROW())) | K34: =IF(OR(J34="",L34=""),"",J34*(1-L34)) | M34: =IF(INDEX(A:A,ROW())="","",IF(INDEX(I:I,ROW())<=0,"ESGOTADO",IF(INDEX(I:I,ROW())<=2,"ÚLTIMAS UNIDADES","DISPONÍVEL")))
H35: {=IF(INDEX(A:A,ROW())="","",SUMIF(Vendas!$B$5:$B$504,INDEX(A:A,ROW()),Vendas!$D$5:$D$504))} | I35: =IF(INDEX(A:A,ROW())="","",INDEX(G:G,ROW())-INDEX(H:H,ROW())) | K35: =IF(OR(J35="",L35=""),"",J35*(1-L35)) | M35: =IF(INDEX(A:A,ROW())="","",IF(INDEX(I:I,ROW())<=0,"ESGOTADO",IF(INDEX(I:I,ROW())<=2,"ÚLTIMAS UNIDADES","DISPONÍVEL")))
H36: {=IF(INDEX(A:A,ROW())="","",SUMIF(Vendas!$B$5:$B$504,INDEX(A:A,ROW()),Vendas!$D$5:$D$504))} | I36: =IF(INDEX(A:A,ROW())="","",INDEX(G:G,ROW())-INDEX(H:H,ROW())) | K36: =IF(OR(J36="",L36=""),"",J36*(1-L36)) | M36: =IF(INDEX(A:A,ROW())="","",IF(INDEX(I:I,ROW())<=0,"ESGOTADO",IF(INDEX(I:I,ROW())<=2,"ÚLTIMAS UNIDADES","DISPONÍVEL")))
H37: {=IF(INDEX(A:A,ROW())="","",SUMIF(Vendas!$B$5:$B$504,INDEX(A:A,ROW()),Vendas!$D$5:$D$504))} | I37: =IF(INDEX(A:A,ROW())="","",INDEX(G:G,ROW())-INDEX(H:H,ROW())) | K37: =IF(OR(J37="",L37=""),"",J37*(1-L37)) | M37: =IF(INDEX(A:A,ROW())="","",IF(INDEX(I:I,ROW())<=0,"ESGOTADO",IF(INDEX(I:I,ROW())<=2,"ÚLTIMAS UNIDADES","DISPONÍVEL")))
H38: {=IF(INDEX(A:A,ROW())="","",SUMIF(Vendas!$B$5:$B$504,INDEX(A:A,ROW()),Vendas!$D$5:$D$504))} | I38: =IF(INDEX(A:A,ROW())="","",INDEX(G:G,ROW())-INDEX(H:H,ROW())) | K38: =IF(OR(J38="",L38=""),"",J38*(1-L38)) | M38: =IF(INDEX(A:A,ROW())="","",IF(INDEX(I:I,ROW())<=0,"ESGOTADO",IF(INDEX(I:I,ROW())<=2,"ÚLTIMAS UNIDADES","DISPONÍVEL")))
H39: {=IF(INDEX(A:A,ROW())="","",SUMIF(Vendas!$B$5:$B$504,INDEX(A:A,ROW()),Vendas!$D$5:$D$504))} | I39: =IF(INDEX(A:A,ROW())="","",INDEX(G:G,ROW())-INDEX(H:H,ROW())) | K39: =IF(OR(J39="",L39=""),"",J39*(1-L39)) | M39: =IF(INDEX(A:A,ROW())="","",IF(INDEX(I:I,ROW())<=0,"ESGOTADO",IF(INDEX(I:I,ROW())<=2,"ÚLTIMAS UNIDADES","DISPONÍVEL")))
H40: {=IF(INDEX(A:A,ROW())="","",SUMIF(Vendas!$B$5:$B$504,INDEX(A:A,ROW()),Vendas!$D$5:$D$504))} | I40: =IF(INDEX(A:A,ROW())="","",INDEX(G:G,ROW())-INDEX(H:H,ROW())) | K40: =IF(OR(J40="",L40=""),"",J40*(1-L40)) | M40: =IF(INDEX(A:A,ROW())="","",IF(INDEX(I:I,ROW())<=0,"ESGOTADO",IF(INDEX(I:I,ROW())<=2,"ÚLTIMAS UNIDADES","DISPONÍVEL")))
H41: {=IF(INDEX(A:A,ROW())="","",SUMIF(Vendas!$B$5:$B$504,INDEX(A:A,ROW()),Vendas!$D$5:$D$504))} | I41: =IF(INDEX(A:A,ROW())="","",INDEX(G:G,ROW())-INDEX(H:H,ROW())) | K41: =IF(OR(J41="",L41=""),"",J41*(1-L41)) | M41: =IF(INDEX(A:A,ROW())="","",IF(INDEX(I:I,ROW())<=0,"ESGOTADO",IF(INDEX(I:I,ROW())<=2,"ÚLTIMAS UNIDADES","DISPONÍVEL")))
H42: {=IF(INDEX(A:A,ROW())="","",SUMIF(Vendas!$B$5:$B$504,INDEX(A:A,ROW()),Vendas!$D$5:$D$504))} | I42: =IF(INDEX(A:A,ROW())="","",INDEX(G:G,ROW())-INDEX(H:H,ROW())) | K42: =IF(OR(J42="",L42=""),"",J42*(1-L42)) | M42: =IF(INDEX(A:A,ROW())="","",IF(INDEX(I:I,ROW())<=0,"ESGOTADO",IF(INDEX(I:I,ROW())<=2,"ÚLTIMAS UNIDADES","DISPONÍVEL")))
... H107: {=IF(INDEX(A:A,ROW())="","",SUMIF(Vendas!$B$5:$B$504,INDEX(A:A,ROW()),Vendas!$D$5:$D$504))} | I107: =IF(INDEX(A:A,ROW())="","",INDEX(G:G,ROW())-INDEX(H:H,ROW())) | K107: =IF(OR(J107="",L107=""),"",J107*(1-L107)) | M107: =IF(INDEX(A:A,ROW())="","",IF(INDEX(I:I,ROW())<=0,"ESGOTADO",IF(INDEX(I:I,ROW())<=2,"ÚLTIMAS UNIDADES","DISPONÍVEL")))

Sheet Vendas
A1: REGISTRO DE VENDAS — BAZAR PURE
A2: Total vendido | B2: =SUM(F5:F504) -> 0 | D2: Nº de vendas | E2: =COUNT(A5:A504) -> 0 | G2: Unidades vendidas | H2: =SUM(D5:D504) -> 0
A3: Preencha data, código, quantidade, cliente, pagamento e status. Produto e preço são buscados automaticamente.
A4: Data da Venda | B4: Código | C4: Produto | D4: Quantidade | E4: Preço Unit. | F4: Total | G4: Cliente | H4: Pagamento | I4: Status | J4: Observações
C5: {=IF(INDEX(B:B,ROW())="","",VLOOKUP(INDEX(B:B,ROW()),'Produtos Bazar'!$A$8:$K$107,2,FALSE))} | E5: {=IF(INDEX(B:B,ROW())="","",VLOOKUP(INDEX(B:B,ROW()),'Produtos Bazar'!$A$8:$K$107,11,FALSE))} | F5: =IF(OR(INDEX(D:D,ROW())="",INDEX(E:E,ROW())=""),"",INDEX(D:D,ROW())*INDEX(E:E,ROW()))
C6: {=IF(INDEX(B:B,ROW())="","",VLOOKUP(INDEX(B:B,ROW()),'Produtos Bazar'!$A$8:$K$107,2,FALSE))} | E6: {=IF(INDEX(B:B,ROW())="","",VLOOKUP(INDEX(B:B,ROW()),'Produtos Bazar'!$A$8:$K$107,11,FALSE))} | F6: =IF(OR(INDEX(D:D,ROW())="",INDEX(E:E,ROW())=""),"",INDEX(D:D,ROW())*INDEX(E:E,ROW()))
C7: {=IF(INDEX(B:B,ROW())="","",VLOOKUP(INDEX(B:B,ROW()),'Produtos Bazar'!$A$8:$K$107,2,FALSE))} | E7: {=IF(INDEX(B:B,ROW())="","",VLOOKUP(INDEX(B:B,ROW()),'Produtos Bazar'!$A$8:$K$107,11,FALSE))} | F7: =IF(OR(INDEX(D:D,ROW())="",INDEX(E:E,ROW())=""),"",INDEX(D:D,ROW())*INDEX(E:E,ROW()))
C8: {=IF(INDEX(B:B,ROW())="","",VLOOKUP(INDEX(B:B,ROW()),'Produtos Bazar'!$A$8:$K$107,2,FALSE))} | E8: {=IF(INDEX(B:B,ROW())="","",VLOOKUP(INDEX(B:B,ROW()),'Produtos Bazar'!$A$8:$K$107,11,FALSE))} | F8: =IF(OR(INDEX(D:D,ROW())="",INDEX(E:E,ROW())=""),"",INDEX(D:D,ROW())*INDEX(E:E,ROW()))
C9: {=IF(INDEX(B:B,ROW())="","",VLOOKUP(INDEX(B:B,ROW()),'Produtos Bazar'!$A$8:$K$107,2,FALSE))} | E9: {=IF(INDEX(B:B,ROW())="","",VLOOKUP(INDEX(B:B,ROW()),'Produtos Bazar'!$A$8:$K$107,11,FALSE))} | F9: =IF(OR(INDEX(D:D,ROW())="",INDEX(E:E,ROW())=""),"",INDEX(D:D,ROW())*INDEX(E:E,ROW()))
C10: {=IF(INDEX(B:B,ROW())="","",VLOOKUP(INDEX(B:B,ROW()),'Produtos Bazar'!$A$8:$K$107,2,FALSE))} | E10: {=IF(INDEX(B:B,ROW())="","",VLOOKUP(INDEX(B:B,ROW()),'Produtos Bazar'!$A$8:$K$107,11,FALSE))} | F10: =IF(OR(INDEX(D:D,ROW())="",INDEX(E:E,ROW())=""),"",INDEX(D:D,ROW())*INDEX(E:E,ROW()))
C11: {=IF(INDEX(B:B,ROW())="","",VLOOKUP(INDEX(B:B,ROW()),'Produtos Bazar'!$A$8:$K$107,2,FALSE))} | E11: {=IF(INDEX(B:B,ROW())="","",VLOOKUP(INDEX(B:B,ROW()),'Produtos Bazar'!$A$8:$K$107,11,FALSE))} | F11: =IF(OR(INDEX(D:D,ROW())="",INDEX(E:E,ROW())=""),"",INDEX(D:D,ROW())*INDEX(E:E,ROW()))
C12: {=IF(INDEX(B:B,ROW())="","",VLOOKUP(INDEX(B:B,ROW()),'Produtos Bazar'!$A$8:$K$107,2,FALSE))} | E12: {=IF(INDEX(B:B,ROW())="","",VLOOKUP(INDEX(B:B,ROW()),'Produtos Bazar'!$A$8:$K$107,11,FALSE))} | F12: =IF(OR(INDEX(D:D,ROW())="",INDEX(E:E,ROW())=""),"",INDEX(D:D,ROW())*INDEX(E:E,ROW()))
C13: {=IF(INDEX(B:B,ROW())="","",VLOOKUP(INDEX(B:B,ROW()),'Produtos Bazar'!$A$8:$K$107,2,FALSE))} | E13: {=IF(INDEX(B:B,ROW())="","",VLOOKUP(INDEX(B:B,ROW()),'Produtos Bazar'!$A$8:$K$107,11,FALSE))} | F13: =IF(OR(INDEX(D:D,ROW())="",INDEX(E:E,ROW())=""),"",INDEX(D:D,ROW())*INDEX(E:E,ROW()))
C14: {=IF(INDEX(B:B,ROW())="","",VLOOKUP(INDEX(B:B,ROW()),'Produtos Bazar'!$A$8:$K$107,2,FALSE))} | E14: {=IF(INDEX(B:B,ROW())="","",VLOOKUP(INDEX(B:B,ROW()),'Produtos Bazar'!$A$8:$K$107,11,FALSE))} | F14: =IF(OR(INDEX(D:D,ROW())="",INDEX(E:E,ROW())=""),"",INDEX(D:D,ROW())*INDEX(E:E,ROW()))
C15: {=IF(INDEX(B:B,ROW())="","",VLOOKUP(INDEX(B:B,ROW()),'Produtos Bazar'!$A$8:$K$107,2,FALSE))} | E15: {=IF(INDEX(B:B,ROW())="","",VLOOKUP(INDEX(B:B,ROW()),'Produtos Bazar'!$A$8:$K$107,11,FALSE))} | F15: =IF(OR(INDEX(D:D,ROW())="",INDEX(E:E,ROW())=""),"",INDEX(D:D,ROW())*INDEX(E:E,ROW()))
C16: {=IF(INDEX(B:B,ROW())="","",VLOOKUP(INDEX(B:B,ROW()),'Produtos Bazar'!$A$8:$K$107,2,FALSE))} | E16: {=IF(INDEX(B:B,ROW())="","",VLOOKUP(INDEX(B:B,ROW()),'Produtos Bazar'!$A$8:$K$107,11,FALSE))} | F16: =IF(OR(INDEX(D:D,ROW())="",INDEX(E:E,ROW())=""),"",INDEX(D:D,ROW())*INDEX(E:E,ROW()))
... C504: {=IF(INDEX(B:B,ROW())="","",VLOOKUP(INDEX(B:B,ROW()),'Produtos Bazar'!$A$8:$K$107,2,FALSE))} | E504: {=IF(INDEX(B:B,ROW())="","",VLOOKUP(INDEX(B:B,ROW()),'Produtos Bazar'!$A$8:$K$107,11,FALSE))} | F504: =IF(OR(INDEX(D:D,ROW())="",INDEX(E:E,ROW())=""),"",INDEX(D:D,ROW())*INDEX(E:E,ROW()))

Sheet WhatsApp
A1: MENSAGEM FIXADA — PURE PROMOÇÕES
A2: Cadastre os produtos na aba Produtos Bazar. A mensagem abaixo será atualizada automaticamente.
A4: Mensagem de apresentação do grupo
B5: 🌸 *BEM-VINDOS AO BAZAR PURE PROMOÇÕES!* 🌸 Aqui você encontra produtos originais com preços especiais porque a caixa ou embalagem externa foi violada durante o transporte. ✅ Consulte a condição informada de cada item 📸 Peça fotos antes de confirmar 💳 Pagamento e retirada/entrega a combinar ⏳ Produtos sujeitos à disponibilidade Para comprar, envie o nome ou código do produto no grupo.
A8: CATÁLOGO AUTOMÁTICO PARA COPIAR
A9: Copie o conteúdo da célula B10 e fixe no grupo. Atualize sempre que cadastrar ou vender itens.
B10: ="🌸 *BAZAR PURE PROMOÇÕES* 🌸"&CHAR(10)&CHAR(10)&"Produtos originais com preço especial por avaria na caixa/embalagem durante o transporte."&CHAR(10)&"Consulte condição e fotos de cada item."&CHAR(10)&CHAR(10)&TEXTJOIN(CHAR(10)&CHAR(10),TRUE,B14:B113)&CHAR(10)&CHAR(10)&"📲 Para reservar, envie o código ou nome do produto no grupo."&CHAR(10)&"⏳ Estoque sujeito à disponibilidade." -> 🌸 *BAZAR PURE PROMOÇÕES* 🌸 Produtos originais com preço especial por avaria na caixa/embalagem durante o transporte. Consulte condição e fotos de cada item. 📲 Para reservar, envie o código ou nome do produto no grupo. ⏳ Estoque sujeito à disponibilidade.
A12: Linhas individuais dos produtos (geradas automaticamente)
B14: {=IF(INDEX('Produtos Bazar'!A:A,ROW()-6)="","","✨ *"&INDEX('Produtos Bazar'!B:B,ROW()-6)&"*"&IF(INDEX('Produtos Bazar'!C:C,ROW()-6)<>""," | "&INDEX('Produtos Bazar'!C:C,ROW()-6),"")&IF(INDEX('Produtos Bazar'!E:E,ROW()-6)<>""," | "&INDEX('Produtos Bazar'!E:E,ROW()-6),"")&CHAR(10)&"Código: "&INDEX('Produtos Bazar'!A:A,ROW()-6)&CHAR(10)&"Condição: "&INDEX('Produtos Bazar'!F:F,ROW()-6)&CHAR(10)&"De: "&TEXT(INDEX('Produtos Bazar'!J:J,ROW()-6),"R$ #,##0.00")&" | *Por: "&TEXT(INDEX('Produtos Bazar'!K:K,ROW()-6),"R$ #,##0.00")&"* ("&TEXT(INDEX('Produtos Bazar'!L:L,ROW()-6),"0%")&" OFF)"&CHAR(10)&"Disponível: "&INDEX('Produtos Bazar'!I:I,ROW()-6)&" un. | "&INDEX('Produtos Bazar'!M:M,ROW()-6))}
B15: {=IF(INDEX('Produtos Bazar'!A:A,ROW()-6)="","","✨ *"&INDEX('Produtos Bazar'!B:B,ROW()-6)&"*"&IF(INDEX('Produtos Bazar'!C:C,ROW()-6)<>""," | "&INDEX('Produtos Bazar'!C:C,ROW()-6),"")&IF(INDEX('Produtos Bazar'!E:E,ROW()-6)<>""," | "&INDEX('Produtos Bazar'!E:E,ROW()-6),"")&CHAR(10)&"Código: "&INDEX('Produtos Bazar'!A:A,ROW()-6)&CHAR(10)&"Condição: "&INDEX('Produtos Bazar'!F:F,ROW()-6)&CHAR(10)&"De: "&TEXT(INDEX('Produtos Bazar'!J:J,ROW()-6),"R$ #,##0.00")&" | *Por: "&TEXT(INDEX('Produtos Bazar'!K:K,ROW()-6),"R$ #,##0.00")&"* ("&TEXT(INDEX('Produtos Bazar'!L:L,ROW()-6),"0%")&" OFF)"&CHAR(10)&"Disponível: "&INDEX('Produtos Bazar'!I:I,ROW()-6)&" un. | "&INDEX('Produtos Bazar'!M:M,ROW()-6))}
B16: {=IF(INDEX('Produtos Bazar'!A:A,ROW()-6)="","","✨ *"&INDEX('Produtos Bazar'!B:B,ROW()-6)&"*"&IF(INDEX('Produtos Bazar'!C:C,ROW()-6)<>""," | "&INDEX('Produtos Bazar'!C:C,ROW()-6),"")&IF(INDEX('Produtos Bazar'!E:E,ROW()-6)<>""," | "&INDEX('Produtos Bazar'!E:E,ROW()-6),"")&CHAR(10)&"Código: "&INDEX('Produtos Bazar'!A:A,ROW()-6)&CHAR(10)&"Condição: "&INDEX('Produtos Bazar'!F:F,ROW()-6)&CHAR(10)&"De: "&TEXT(INDEX('Produtos Bazar'!J:J,ROW()-6),"R$ #,##0.00")&" | *Por: "&TEXT(INDEX('Produtos Bazar'!K:K,ROW()-6),"R$ #,##0.00")&"* ("&TEXT(INDEX('Produtos Bazar'!L:L,ROW()-6),"0%")&" OFF)"&CHAR(10)&"Disponível: "&INDEX('Produtos Bazar'!I:I,ROW()-6)&" un. | "&INDEX('Produtos Bazar'!M:M,ROW()-6))}
B17: {=IF(INDEX('Produtos Bazar'!A:A,ROW()-6)="","","✨ *"&INDEX('Produtos Bazar'!B:B,ROW()-6)&"*"&IF(INDEX('Produtos Bazar'!C:C,ROW()-6)<>""," | "&INDEX('Produtos Bazar'!C:C,ROW()-6),"")&IF(INDEX('Produtos Bazar'!E:E,ROW()-6)<>""," | "&INDEX('Produtos Bazar'!E:E,ROW()-6),"")&CHAR(10)&"Código: "&INDEX('Produtos Bazar'!A:A,ROW()-6)&CHAR(10)&"Condição: "&INDEX('Produtos Bazar'!F:F,ROW()-6)&CHAR(10)&"De: "&TEXT(INDEX('Produtos Bazar'!J:J,ROW()-6),"R$ #,##0.00")&" | *Por: "&TEXT(INDEX('Produtos Bazar'!K:K,ROW()-6),"R$ #,##0.00")&"* ("&TEXT(INDEX('Produtos Bazar'!L:L,ROW()-6),"0%")&" OFF)"&CHAR(10)&"Disponível: "&INDEX('Produtos Bazar'!I:I,ROW()-6)&" un. | "&INDEX('Produtos Bazar'!M:M,ROW()-6))}
B18: {=IF(INDEX('Produtos Bazar'!A:A,ROW()-6)="","","✨ *"&INDEX('Produtos Bazar'!B:B,ROW()-6)&"*"&IF(INDEX('Produtos Bazar'!C:C,ROW()-6)<>""," | "&INDEX('Produtos Bazar'!C:C,ROW()-6),"")&IF(INDEX('Produtos Bazar'!E:E,ROW()-6)<>""," | "&INDEX('Produtos Bazar'!E:E,ROW()-6),"")&CHAR(10)&"Código: "&INDEX('Produtos Bazar'!A:A,ROW()-6)&CHAR(10)&"Condição: "&INDEX('Produtos Bazar'!F:F,ROW()-6)&CHAR(10)&"De: "&TEXT(INDEX('Produtos Bazar'!J:J,ROW()-6),"R$ #,##0.00")&" | *Por: "&TEXT(INDEX('Produtos Bazar'!K:K,ROW()-6),"R$ #,##0.00")&"* ("&TEXT(INDEX('Produtos Bazar'!L:L,ROW()-6),"0%")&" OFF)"&CHAR(10)&"Disponível: "&INDEX('Produtos Bazar'!I:I,ROW()-6)&" un. | "&INDEX('Produtos Bazar'!M:M,ROW()-6))}
B19: {=IF(INDEX('Produtos Bazar'!A:A,ROW()-6)="","","✨ *"&INDEX('Produtos Bazar'!B:B,ROW()-6)&"*"&IF(INDEX('Produtos Bazar'!C:C,ROW()-6)<>""," | "&INDEX('Produtos Bazar'!C:C,ROW()-6),"")&IF(INDEX('Produtos Bazar'!E:E,ROW()-6)<>""," | "&INDEX('Produtos Bazar'!E:E,ROW()-6),"")&CHAR(10)&"Código: "&INDEX('Produtos Bazar'!A:A,ROW()-6)&CHAR(10)&"Condição: "&INDEX('Produtos Bazar'!F:F,ROW()-6)&CHAR(10)&"De: "&TEXT(INDEX('Produtos Bazar'!J:J,ROW()-6),"R$ #,##0.00")&" | *Por: "&TEXT(INDEX('Produtos Bazar'!K:K,ROW()-6),"R$ #,##0.00")&"* ("&TEXT(INDEX('Produtos Bazar'!L:L,ROW()-6),"0%")&" OFF)"&CHAR(10)&"Disponível: "&INDEX('Produtos Bazar'!I:I,ROW()-6)&" un. | "&INDEX('Produtos Bazar'!M:M,ROW()-6))}
B20: {=IF(INDEX('Produtos Bazar'!A:A,ROW()-6)="","","✨ *"&INDEX('Produtos Bazar'!B:B,ROW()-6)&"*"&IF(INDEX('Produtos Bazar'!C:C,ROW()-6)<>""," | "&INDEX('Produtos Bazar'!C:C,ROW()-6),"")&IF(INDEX('Produtos Bazar'!E:E,ROW()-6)<>""," | "&INDEX('Produtos Bazar'!E:E,ROW()-6),"")&CHAR(10)&"Código: "&INDEX('Produtos Bazar'!A:A,ROW()-6)&CHAR(10)&"Condição: "&INDEX('Produtos Bazar'!F:F,ROW()-6)&CHAR(10)&"De: "&TEXT(INDEX('Produtos Bazar'!J:J,ROW()-6),"R$ #,##0.00")&" | *Por: "&TEXT(INDEX('Produtos Bazar'!K:K,ROW()-6),"R$ #,##0.00")&"* ("&TEXT(INDEX('Produtos Bazar'!L:L,ROW()-6),"0%")&" OFF)"&CHAR(10)&"Disponível: "&INDEX('Produtos Bazar'!I:I,ROW()-6)&" un. | "&INDEX('Produtos Bazar'!M:M,ROW()-6))}
B21: {=IF(INDEX('Produtos Bazar'!A:A,ROW()-6)="","","✨ *"&INDEX('Produtos Bazar'!B:B,ROW()-6)&"*"&IF(INDEX('Produtos Bazar'!C:C,ROW()-6)<>""," | "&INDEX('Produtos Bazar'!C:C,ROW()-6),"")&IF(INDEX('Produtos Bazar'!E:E,ROW()-6)<>""," | "&INDEX('Produtos Bazar'!E:E,ROW()-6),"")&CHAR(10)&"Código: "&INDEX('Produtos Bazar'!A:A,ROW()-6)&CHAR(10)&"Condição: "&INDEX('Produtos Bazar'!F:F,ROW()-6)&CHAR(10)&"De: "&TEXT(INDEX('Produtos Bazar'!J:J,ROW()-6),"R$ #,##0.00")&" | *Por: "&TEXT(INDEX('Produtos Bazar'!K:K,ROW()-6),"R$ #,##0.00")&"* ("&TEXT(INDEX('Produtos Bazar'!L:L,ROW()-6),"0%")&" OFF)"&CHAR(10)&"Disponível: "&INDEX('Produtos Bazar'!I:I,ROW()-6)&" un. | "&INDEX('Produtos Bazar'!M:M,ROW()-6))}
B22: {=IF(INDEX('Produtos Bazar'!A:A,ROW()-6)="","","✨ *"&INDEX('Produtos Bazar'!B:B,ROW()-6)&"*"&IF(INDEX('Produtos Bazar'!C:C,ROW()-6)<>""," | "&INDEX('Produtos Bazar'!C:C,ROW()-6),"")&IF(INDEX('Produtos Bazar'!E:E,ROW()-6)<>""," | "&INDEX('Produtos Bazar'!E:E,ROW()-6),"")&CHAR(10)&"Código: "&INDEX('Produtos Bazar'!A:A,ROW()-6)&CHAR(10)&"Condição: "&INDEX('Produtos Bazar'!F:F,ROW()-6)&CHAR(10)&"De: "&TEXT(INDEX('Produtos Bazar'!J:J,ROW()-6),"R$ #,##0.00")&" | *Por: "&TEXT(INDEX('Produtos Bazar'!K:K,ROW()-6),"R$ #,##0.00")&"* ("&TEXT(INDEX('Produtos Bazar'!L:L,ROW()-6),"0%")&" OFF)"&CHAR(10)&"Disponível: "&INDEX('Produtos Bazar'!I:I,ROW()-6)&" un. | "&INDEX('Produtos Bazar'!M:M,ROW()-6))}
B23: {=IF(INDEX('Produtos Bazar'!A:A,ROW()-6)="","","✨ *"&INDEX('Produtos Bazar'!B:B,ROW()-6)&"*"&IF(INDEX('Produtos Bazar'!C:C,ROW()-6)<>""," | "&INDEX('Produtos Bazar'!C:C,ROW()-6),"")&IF(INDEX('Produtos Bazar'!E:E,ROW()-6)<>""," | "&INDEX('Produtos Bazar'!E:E,ROW()-6),"")&CHAR(10)&"Código: "&INDEX('Produtos Bazar'!A:A,ROW()-6)&CHAR(10)&"Condição: "&INDEX('Produtos Bazar'!F:F,ROW()-6)&CHAR(10)&"De: "&TEXT(INDEX('Produtos Bazar'!J:J,ROW()-6),"R$ #,##0.00")&" | *Por: "&TEXT(INDEX('Produtos Bazar'!K:K,ROW()-6),"R$ #,##0.00")&"* ("&TEXT(INDEX('Produtos Bazar'!L:L,ROW()-6),"0%")&" OFF)"&CHAR(10)&"Disponível: "&INDEX('Produtos Bazar'!I:I,ROW()-6)&" un. | "&INDEX('Produtos Bazar'!M:M,ROW()-6))}
B24: {=IF(INDEX('Produtos Bazar'!A:A,ROW()-6)="","","✨ *"&INDEX('Produtos Bazar'!B:B,ROW()-6)&"*"&IF(INDEX('Produtos Bazar'!C:C,ROW()-6)<>""," | "&INDEX('Produtos Bazar'!C:C,ROW()-6),"")&IF(INDEX('Produtos Bazar'!E:E,ROW()-6)<>""," | "&INDEX('Produtos Bazar'!E:E,ROW()-6),"")&CHAR(10)&"Código: "&INDEX('Produtos Bazar'!A:A,ROW()-6)&CHAR(10)&"Condição: "&INDEX('Produtos Bazar'!F:F,ROW()-6)&CHAR(10)&"De: "&TEXT(INDEX('Produtos Bazar'!J:J,ROW()-6),"R$ #,##0.00")&" | *Por: "&TEXT(INDEX('Produtos Bazar'!K:K,ROW()-6),"R$ #,##0.00")&"* ("&TEXT(INDEX('Produtos Bazar'!L:L,ROW()-6),"0%")&" OFF)"&CHAR(10)&"Disponível: "&INDEX('Produtos Bazar'!I:I,ROW()-6)&" un. | "&INDEX('Produtos Bazar'!M:M,ROW()-6))}
B25: {=IF(INDEX('Produtos Bazar'!A:A,ROW()-6)="","","✨ *"&INDEX('Produtos Bazar'!B:B,ROW()-6)&"*"&IF(INDEX('Produtos Bazar'!C:C,ROW()-6)<>""," | "&INDEX('Produtos Bazar'!C:C,ROW()-6),"")&IF(INDEX('Produtos Bazar'!E:E,ROW()-6)<>""," | "&INDEX('Produtos Bazar'!E:E,ROW()-6),"")&CHAR(10)&"Código: "&INDEX('Produtos Bazar'!A:A,ROW()-6)&CHAR(10)&"Condição: "&INDEX('Produtos Bazar'!F:F,ROW()-6)&CHAR(10)&"De: "&TEXT(INDEX('Produtos Bazar'!J:J,ROW()-6),"R$ #,##0.00")&" | *Por: "&TEXT(INDEX('Produtos Bazar'!K:K,ROW()-6),"R$ #,##0.00")&"* ("&TEXT(INDEX('Produtos Bazar'!L:L,ROW()-6),"0%")&" OFF)"&CHAR(10)&"Disponível: "&INDEX('Produtos Bazar'!I:I,ROW()-6)&" un. | "&INDEX('Produtos Bazar'!M:M,ROW()-6))}
... B113: {=IF(INDEX('Produtos Bazar'!A:A,ROW()-6)="","","✨ *"&INDEX('Produtos Bazar'!B:B,ROW()-6)&"*"&IF(INDEX('Produtos Bazar'!C:C,ROW()-6)<>""," | "&INDEX('Produtos Bazar'!C:C,ROW()-6),"")&IF(INDEX('Produtos Bazar'!E:E,ROW()-6)<>""," | "&INDEX('Produtos Bazar'!E:E,ROW()-6),"")&CHAR(10)&"Código: "&INDEX('Produtos Bazar'!A:A,ROW()-6)&CHAR(10)&"Condição: "&INDEX('Produtos Bazar'!F:F,ROW()-6)&CHAR(10)&"De: "&TEXT(INDEX('Produtos Bazar'!J:J,ROW()-6),"R$ #,##0.00")&" | *Por: "&TEXT(INDEX('Produtos Bazar'!K:K,ROW()-6),"R$ #,##0.00")&"* ("&TEXT(INDEX('Produtos Bazar'!L:L,ROW()-6),"0%")&" OFF)"&CHAR(10)&"Disponível: "&INDEX('Produtos Bazar'!I:I,ROW()-6)&" un. | "&INDEX('Produtos Bazar'!M:M,ROW()-6))}
